demoazure/__init__.py
demoazure-0.1.6.dist-info/METADATA
demoazure-0.1.6.dist-info/WHEEL
demoazure-0.1.6.dist-info/RECORD
